{
  "query": "Data structures courses, specifically CS 1332 or equivalent",
  "category": "mixed",
  "expected_courses": [
    "CS 1332"
  ],
  "execution_times": {
    "embedding": 0.7215774059295654,
    "id_matching": 0.0015306472778320312,
    "combined": 0.6949641704559326
  },
  "metrics": {
    "result_counts": {
      "embedding": 20,
      "id_matching": 1,
      "combined": 20
    },
    "overlap": {
      "embedding_vs_combined": 1.0,
      "id_vs_combined": 0.05,
      "embedding_vs_id": 0.05
    },
    "rank_correlations": {
      "embedding_vs_combined": [
        0.8421052631578947,
        20
      ],
      "id_vs_combined": [
        0.0,
        1
      ],
      "embedding_vs_id": [
        0.0,
        1
      ]
    },
    "coverage": {
      "embedding": {
        "found_count": 1,
        "total_expected": 1,
        "coverage_ratio": 1.0
      },
      "id_matching": {
        "found_count": 1,
        "total_expected": 1,
        "coverage_ratio": 1.0
      },
      "combined": {
        "found_count": 1,
        "total_expected": 1,
        "coverage_ratio": 1.0
      }
    }
  },
  "result_counts": {
    "embedding": 20,
    "id_matching": 1,
    "combined": 20
  }
}